<?xml version="1.0" encoding="UTF-8"?>
<faultRecord>
  <faultRecord time="10" type="timeover" object="软件_3930" isFalseAlarm="False" isSuccessRebuild="True" redundancyBefore="-1" redundancyAfter="-1" faultType="" ifEmpty="False" />
  <faultRecord time="10" type="timeover" object="软件_3931" isFalseAlarm="False" isSuccessRebuild="True" redundancyBefore="-1" redundancyAfter="-1" faultType="" ifEmpty="False" />
  <faultRecord time="12.62" type="rebuild" object="udp_tcp" isFalseAlarm="True" isSuccessRebuild="True" redundancyBefore="2" redundancyAfter="8.12" faultType="CPU" ifEmpty="False">
    <host name="udp_tcp2">
      <cal cal="最少请求优先级得分：" />
      <cal cal="                CPU分 = 1 - CPU利用率 = 1 - 0 = 1" />
      <cal cal="                内存分 = 1 - 内存利用率 = 1 - 0 = 1" />
      <cal cal="                总得分 = 10 * （CPU分 + 内存分）/2 = 10" />
      <cal cal="资源均衡度得分：" />
      <cal cal="                方差 = (（CPU利用率 - 平均利用率）^2 + （内存利用率 - 平均利用率）^2 ) / 2 = 0" />
      <cal cal="                总得分 = 10 * （1 - 方差） = 10" />
      <cal cal="总得分 = （最少请求优先级得分 + 资源均衡度得分） / 2 = 10" />
    </host>
    <host name="udp_tcp3">
      <cal cal="最少请求优先级得分：" />
      <cal cal="                CPU分 = 1 - CPU利用率 = 1 - 0 = 1" />
      <cal cal="                内存分 = 1 - 内存利用率 = 1 - 0 = 1" />
      <cal cal="                总得分 = 10 * （CPU分 + 内存分）/2 = 10" />
      <cal cal="资源均衡度得分：" />
      <cal cal="                方差 = (（CPU利用率 - 平均利用率）^2 + （内存利用率 - 平均利用率）^2 ) / 2 = 0" />
      <cal cal="                总得分 = 10 * （1 - 方差） = 10" />
      <cal cal="总得分 = （最少请求优先级得分 + 资源均衡度得分） / 2 = 10" />
    </host>
  </faultRecord>
  <faultRecord time="20" type="timeover" object="软件_3930" isFalseAlarm="False" isSuccessRebuild="True" redundancyBefore="-1" redundancyAfter="-1" faultType="" ifEmpty="False" />
  <faultRecord time="20" type="timeover" object="软件_3931" isFalseAlarm="False" isSuccessRebuild="True" redundancyBefore="-1" redundancyAfter="-1" faultType="" ifEmpty="False" />
  <faultRecord time="30" type="timeover" object="软件_3930" isFalseAlarm="False" isSuccessRebuild="True" redundancyBefore="-1" redundancyAfter="-1" faultType="" ifEmpty="False" />
  <faultRecord time="30" type="timeover" object="软件_3931" isFalseAlarm="False" isSuccessRebuild="True" redundancyBefore="-1" redundancyAfter="-1" faultType="" ifEmpty="False" />
  <faultRecord time="33.7" type="rebuild" object="udp_tcp" isFalseAlarm="True" isSuccessRebuild="True" redundancyBefore="2" redundancyAfter="8.12" faultType="CPU" ifEmpty="True">
    <host name="udp_tcp2">
      <cal cal="最少请求优先级得分：" />
      <cal cal="                CPU分 = 1 - CPU利用率 = 1 - 1 = 0" />
      <cal cal="                内存分 = 1 - 内存利用率 = 1 - 0 = 1" />
      <cal cal="                总得分 = 10 * （CPU分 + 内存分）/2 = 5" />
      <cal cal="资源均衡度得分：" />
      <cal cal="                方差 = (（CPU利用率 - 平均利用率）^2 + （内存利用率 - 平均利用率）^2 ) / 2 = 0.25" />
      <cal cal="                总得分 = 10 * （1 - 方差） = 7.5" />
      <cal cal="总得分 = （最少请求优先级得分 + 资源均衡度得分） / 2 = 6.25" />
    </host>
    <host name="udp_tcp3">
      <cal cal="最少请求优先级得分：" />
      <cal cal="                CPU分 = 1 - CPU利用率 = 1 - 0 = 1" />
      <cal cal="                内存分 = 1 - 内存利用率 = 1 - 0 = 1" />
      <cal cal="                总得分 = 10 * （CPU分 + 内存分）/2 = 10" />
      <cal cal="资源均衡度得分：" />
      <cal cal="                方差 = (（CPU利用率 - 平均利用率）^2 + （内存利用率 - 平均利用率）^2 ) / 2 = 0" />
      <cal cal="                总得分 = 10 * （1 - 方差） = 10" />
      <cal cal="总得分 = （最少请求优先级得分 + 资源均衡度得分） / 2 = 10" />
    </host>
  </faultRecord>
  <faultRecord time="40" type="timeover" object="软件_3930" isFalseAlarm="False" isSuccessRebuild="True" redundancyBefore="-1" redundancyAfter="-1" faultType="" ifEmpty="False" />
  <faultRecord time="40" type="timeover" object="软件_3931" isFalseAlarm="False" isSuccessRebuild="True" redundancyBefore="-1" redundancyAfter="-1" faultType="" ifEmpty="False" />
  <faultRecord time="50" type="timeover" object="软件_3930" isFalseAlarm="False" isSuccessRebuild="True" redundancyBefore="-1" redundancyAfter="-1" faultType="" ifEmpty="False" />
  <faultRecord time="50" type="timeover" object="软件_3931" isFalseAlarm="False" isSuccessRebuild="True" redundancyBefore="-1" redundancyAfter="-1" faultType="" ifEmpty="False" />
  <faultRecord time="56.31" type="rebuild" object="udp_tcp" isFalseAlarm="True" isSuccessRebuild="True" redundancyBefore="2" redundancyAfter="8.12" faultType="CPU" ifEmpty="True">
    <host name="udp_tcp2">
      <cal cal="最少请求优先级得分：" />
      <cal cal="                CPU分 = 1 - CPU利用率 = 1 - 1 = 0" />
      <cal cal="                内存分 = 1 - 内存利用率 = 1 - 0 = 1" />
      <cal cal="                总得分 = 10 * （CPU分 + 内存分）/2 = 5" />
      <cal cal="资源均衡度得分：" />
      <cal cal="                方差 = (（CPU利用率 - 平均利用率）^2 + （内存利用率 - 平均利用率）^2 ) / 2 = 0.25" />
      <cal cal="                总得分 = 10 * （1 - 方差） = 7.5" />
      <cal cal="总得分 = （最少请求优先级得分 + 资源均衡度得分） / 2 = 6.25" />
    </host>
    <host name="udp_tcp3">
      <cal cal="最少请求优先级得分：" />
      <cal cal="                CPU分 = 1 - CPU利用率 = 1 - 0 = 1" />
      <cal cal="                内存分 = 1 - 内存利用率 = 1 - 0 = 1" />
      <cal cal="                总得分 = 10 * （CPU分 + 内存分）/2 = 10" />
      <cal cal="资源均衡度得分：" />
      <cal cal="                方差 = (（CPU利用率 - 平均利用率）^2 + （内存利用率 - 平均利用率）^2 ) / 2 = 0" />
      <cal cal="                总得分 = 10 * （1 - 方差） = 10" />
      <cal cal="总得分 = （最少请求优先级得分 + 资源均衡度得分） / 2 = 10" />
    </host>
  </faultRecord>
  <faultRecord time="60" type="timeover" object="软件_3930" isFalseAlarm="False" isSuccessRebuild="True" redundancyBefore="-1" redundancyAfter="-1" faultType="" ifEmpty="False" />
  <faultRecord time="60" type="timeover" object="软件_3931" isFalseAlarm="False" isSuccessRebuild="True" redundancyBefore="-1" redundancyAfter="-1" faultType="" ifEmpty="False" />
  <faultRecord time="70" type="timeover" object="软件_3930" isFalseAlarm="False" isSuccessRebuild="True" redundancyBefore="-1" redundancyAfter="-1" faultType="" ifEmpty="False" />
  <faultRecord time="70" type="timeover" object="软件_3931" isFalseAlarm="False" isSuccessRebuild="True" redundancyBefore="-1" redundancyAfter="-1" faultType="" ifEmpty="False" />
  <faultRecord time="71.76" type="rebuild" object="udp_tcp" isFalseAlarm="True" isSuccessRebuild="True" redundancyBefore="2" redundancyAfter="8.12" faultType="CPU" ifEmpty="True">
    <host name="udp_tcp2">
      <cal cal="最少请求优先级得分：" />
      <cal cal="                CPU分 = 1 - CPU利用率 = 1 - 1 = 0" />
      <cal cal="                内存分 = 1 - 内存利用率 = 1 - 0 = 1" />
      <cal cal="                总得分 = 10 * （CPU分 + 内存分）/2 = 5" />
      <cal cal="资源均衡度得分：" />
      <cal cal="                方差 = (（CPU利用率 - 平均利用率）^2 + （内存利用率 - 平均利用率）^2 ) / 2 = 0.25" />
      <cal cal="                总得分 = 10 * （1 - 方差） = 7.5" />
      <cal cal="总得分 = （最少请求优先级得分 + 资源均衡度得分） / 2 = 6.25" />
    </host>
    <host name="udp_tcp3">
      <cal cal="最少请求优先级得分：" />
      <cal cal="                CPU分 = 1 - CPU利用率 = 1 - 0 = 1" />
      <cal cal="                内存分 = 1 - 内存利用率 = 1 - 0 = 1" />
      <cal cal="                总得分 = 10 * （CPU分 + 内存分）/2 = 10" />
      <cal cal="资源均衡度得分：" />
      <cal cal="                方差 = (（CPU利用率 - 平均利用率）^2 + （内存利用率 - 平均利用率）^2 ) / 2 = 0" />
      <cal cal="                总得分 = 10 * （1 - 方差） = 10" />
      <cal cal="总得分 = （最少请求优先级得分 + 资源均衡度得分） / 2 = 10" />
    </host>
  </faultRecord>
  <faultRecord time="80" type="timeover" object="软件_3930" isFalseAlarm="False" isSuccessRebuild="True" redundancyBefore="-1" redundancyAfter="-1" faultType="" ifEmpty="False" />
  <faultRecord time="80" type="timeover" object="软件_3931" isFalseAlarm="False" isSuccessRebuild="True" redundancyBefore="-1" redundancyAfter="-1" faultType="" ifEmpty="False" />
  <faultRecord time="90" type="timeover" object="软件_3930" isFalseAlarm="False" isSuccessRebuild="True" redundancyBefore="-1" redundancyAfter="-1" faultType="" ifEmpty="False" />
  <faultRecord time="90" type="timeover" object="软件_3931" isFalseAlarm="False" isSuccessRebuild="True" redundancyBefore="-1" redundancyAfter="-1" faultType="" ifEmpty="False" />
  <faultRecord time="94.27" type="rebuild" object="udp_tcp" isFalseAlarm="True" isSuccessRebuild="True" redundancyBefore="2" redundancyAfter="8.12" faultType="CPU" ifEmpty="True">
    <host name="udp_tcp2">
      <cal cal="最少请求优先级得分：" />
      <cal cal="                CPU分 = 1 - CPU利用率 = 1 - 1 = 0" />
      <cal cal="                内存分 = 1 - 内存利用率 = 1 - 0 = 1" />
      <cal cal="                总得分 = 10 * （CPU分 + 内存分）/2 = 5" />
      <cal cal="资源均衡度得分：" />
      <cal cal="                方差 = (（CPU利用率 - 平均利用率）^2 + （内存利用率 - 平均利用率）^2 ) / 2 = 0.25" />
      <cal cal="                总得分 = 10 * （1 - 方差） = 7.5" />
      <cal cal="总得分 = （最少请求优先级得分 + 资源均衡度得分） / 2 = 6.25" />
    </host>
    <host name="udp_tcp3">
      <cal cal="最少请求优先级得分：" />
      <cal cal="                CPU分 = 1 - CPU利用率 = 1 - 0 = 1" />
      <cal cal="                内存分 = 1 - 内存利用率 = 1 - 0 = 1" />
      <cal cal="                总得分 = 10 * （CPU分 + 内存分）/2 = 10" />
      <cal cal="资源均衡度得分：" />
      <cal cal="                方差 = (（CPU利用率 - 平均利用率）^2 + （内存利用率 - 平均利用率）^2 ) / 2 = 0" />
      <cal cal="                总得分 = 10 * （1 - 方差） = 10" />
      <cal cal="总得分 = （最少请求优先级得分 + 资源均衡度得分） / 2 = 10" />
    </host>
  </faultRecord>
  <reliability value="1" />
</faultRecord>
